Decision_if/design.sv
module Decision_if (I, O);
input [3:0] I; 
output [3:1] O; 
reg [3:1] O;

always@ (I)
begin
    if (I == 4'b0000)
        O[3] = 1;
    else if (I == 4'b0001)
        O[3] = 1;
    else if (I == 4'b0010)
        O[3] = 1;
    else if (I == 4'b0100)
        O[3] = 1;
    else if (I == 4'b1000)
        O[3] = 1;
    else
        O[3] = 0;

    if (I == 4'b0011)
        O[2] = 1;
    else if (I == 4'b0101)
        O[2] = 1;
    else if (I == 4'b0110)
        O[2] = 1;
    else if (I == 4'b1001)
        O[2] = 1;
    else if (I == 4'b1010)
        O[2] = 1;
    else if (I == 4'b1100)
        O[2] = 1;
    else
        O[2] = 0;

    if (I == 4'b1110 || I == 4'b1101 || I ==4'b1011 || I == 4'b0111 || I == 4'b1111)
        O[1] = 1;
    else
        O[1] = 0;

end
endmodule

Decision_if/testbench.sv
module Decision_if_tb;
    reg [3:0] Input;
    wire  [3:1] Output;
    Decision_if Decision_1(.I(Input),.O(Output));
initial
begin
    #160 $finish;
end
initial
begin
    #0   Input = 4'b0000;
    #10  Input = 4'b0001;
    #10  Input = 4'b0010;
    #10  Input = 4'b0011;
    #10  Input = 4'b0100;
    #10  Input = 4'b0101;
    #10  Input = 4'b0110;
    #10  Input = 4'b0111;
    #10  Input = 4'b1000;
    #10  Input = 4'b1001;
    #10  Input = 4'b1010;
    #10  Input = 4'b1011;
    #10  Input = 4'b1100;
    #10  Input = 4'b1101;
    #10  Input = 4'b1110;
    #10  Input = 4'b1111;
end
initial
begin
  $dumpfile("0424.vcd");
  $dumpvars(0, Decision_1);
end
endmodule

Decision_if/0424.vcd
$date
	Sat Apr 23 16:46:37 2022
$end
$version
	Icarus Verilog
$end
$timescale
	1s
$end
$scope module Decision_if_tb $end
$scope module Decision_1 $end
$var wire 4 ! I [3:0] $end
$var reg 3 " O [3:1] $end
$upscope $end
$upscope $end
$enddefinitions $end
#0
$dumpvars
b100 "
b0 !
$end
#10
b1 !
#20
b10 !
#30
b10 "
b11 !
#40
b100 "
b100 !
#50
b10 "
b101 !
#60
b110 !
#70
b1 "
b111 !
#80
b100 "
b1000 !
#90
b10 "
b1001 !
#100
b1010 !
#110
b1 "
b1011 !
#120
b10 "
b1100 !
#130
b1 "
b1101 !
#140
b1110 !
#150
b1111 !
